biar-0.7.4.dist-info/METADATA
biar-0.7.4.dist-info/WHEEL
biar-0.7.4.dist-info/entry_points.txt
biar-0.7.4.dist-info/licenses/LICENSE
biar/__init__.py
biar/__metadata__.py
biar/errors.py
biar/model.py
biar/py.typed
biar/services.py
biar/user_agents.py
biar-0.7.4.dist-info/RECORD
