Metadata-Version: 2.1
Name: biar
Version: 0.7.4
Summary: batteries-included async requests tool for python.
Author: Rafael Leinio
License: MIT
Project-URL: repository, https://github.com/rafaelleinio/biar
Requires-Python: >=3.11
Requires-Dist: loguru<1.0.0,>=0.7.2
Requires-Dist: pydantic<3.0.0,>=2.8.2
Requires-Dist: tenacity<10.0.0,>=9.0.0
Requires-Dist: pyrate-limiter<4.0.0,>=3.7.0
Requires-Dist: yarl<2.0.0,>=1.18.3
Requires-Dist: certifi>=2025.1.31
Requires-Dist: aiodns<4.0.0,>=3.2.0
Requires-Dist: aiohttp<4.0.0,>=3.11.16
